{
   "agent": "Rocket",
   "behavior": "OK",
   "behaviorClose": "OK",
   "case": 67,
   "closedByMe": true,
   "createStats": true,
   "createWirelog": true,
   "description": "Send fragmented text message, 3 fragments, first and last of length 0, middle non-empty.",
   "droppedByMe": false,
   "duration": 7,
   "expectation": "A message is echo'ed back to us (with payload = payload of middle fragment).",
   "expected": {
      "OK": [
         [
            "message",
            "middle frame payload",
            false
         ]
      ]
   },
   "expectedClose": {
      "closeCode": [
         1000
      ],
      "closedByMe": true,
      "requireClean": true
   },
   "failedByMe": false,
   "httpRequest": "GET /echo HTTP/1.1\r\nUser-Agent: AutobahnTestSuite/0.8.0-0.10.9\r\nHost: host.docker.internal:9001\r\nUpgrade: WebSocket\r\nConnection: Upgrade\r\nPragma: no-cache\r\nCache-Control: no-cache\r\nSec-WebSocket-Key: krG1bNeeL0j6/j3Qam4CMQ==\r\nSec-WebSocket-Version: 13\r\n\r\n",
   "httpResponse": "HTTP/1.1 101 Switching Protocols\r\nconnection: Upgrade\r\nupgrade: websocket\r\nsec-websocket-accept: aokOpSTMm0A8z7pmxg/9z8S25ko=\r\nserver: Rocket\r\ncontent-length: 0\r\ndate: Fri, 01 Jan 2021 03:26:08 GMT\r\n\r\n",
   "id": "6.1.3",
   "isServer": false,
   "localCloseCode": 1000,
   "localCloseReason": null,
   "received": [
      [
         "message",
         "middle frame payload",
         false
      ]
   ],
   "remoteCloseCode": 1000,
   "remoteCloseReason": null,
   "reportCompressionRatio": false,
   "reportTime": false,
   "result": "Actual events match at least one expected.",
   "resultClose": "Connection was properly closed",
   "rxFrameStats": {
      "1": 1,
      "8": 1
   },
   "rxOctetStats": {
      "4": 1,
      "22": 1,
      "201": 1
   },
   "started": "2021-01-01T03:26:09.888Z",
   "trafficStats": null,
   "txFrameStats": {
      "0": 2,
      "1": 1,
      "8": 1
   },
   "txOctetStats": {
      "6": 2,
      "8": 1,
      "26": 1,
      "255": 1
   },
   "wasClean": true,
   "wasCloseHandshakeTimeout": false,
   "wasNotCleanReason": null,
   "wasOpenHandshakeTimeout": false,
   "wasServerConnectionDropTimeout": false,
   "wirelog": [
      [
         "TO",
         [
            255,
            "474554202f6563686f20485454502f312e310d0a557365722d4167656e743a204175746f6261686e5465737453756974652f302e382e302d302e31302e390d0a ..."
         ],
         false
      ],
      [
         "RO",
         [
            201,
            "485454502f312e312031303120537769746368696e672050726f746f636f6c730d0a636f6e6e656374696f6e3a20557067726164650d0a757067726164653a20 ..."
         ]
      ],
      [
         "TF",
         [
            0,
            ""
         ],
         1,
         false,
         0,
         "acaea7f2",
         null,
         null,
         false
      ],
      [
         "TO",
         [
            6,
            "0180acaea7f2"
         ],
         false
      ],
      [
         "TF",
         [
            20,
            "middle frame payload"
         ],
         0,
         false,
         0,
         "2f2e8f35",
         null,
         null,
         false
      ],
      [
         "TO",
         [
            26,
            "00942f2e8f354247eb51434baf535d4fe2500f5eee4c4341ee51"
         ],
         false
      ],
      [
         "TF",
         [
            0,
            ""
         ],
         0,
         true,
         0,
         "a053755e",
         null,
         null,
         false
      ],
      [
         "TO",
         [
            6,
            "8080a053755e"
         ],
         false
      ],
      [
         "TI",
         1
      ],
      [
         "RO",
         [
            22,
            "81146d6964646c65206672616d65207061796c6f6164"
         ]
      ],
      [
         "RF",
         [
            20,
            "middle frame payload"
         ],
         1,
         true,
         0,
         false,
         null
      ],
      [
         "TF",
         [
            2,
            "0x03e8"
         ],
         8,
         true,
         0,
         "4e0367d4",
         null,
         null,
         false
      ],
      [
         "TO",
         [
            8,
            "88824e0367d44deb"
         ],
         false
      ],
      [
         "RO",
         [
            4,
            "880203e8"
         ]
      ],
      [
         "RF",
         [
            2,
            "0x03e8"
         ],
         8,
         true,
         0,
         false,
         null
      ]
   ]
}